{
  "id": "WCSPREW020260528em5s00001",
  "index": 3,
  "scraped_at": "2026-05-28T22:43:29Z",
  "title": "SMC demands tougher super safeguards following billion-dollar failures",
  "full_text": "The Super Members Council (SMC) has urged the federal government to overhaul consumer protections across parts of the superannuation system it believes are vulnerable to weak oversight, following the collapses of Shield and First Guardian.\nIn a submission to the Treasury, the council argued governance, accountability and consumer safety obligations applying to platforms and SMSFs should be brought into line with standards already imposed on APRA-regulated super funds.\nThe push comes after almost 12,000 Australians lost more than $1 billion through the two failed investment schemes, which the council said exposed significant regulatory weaknesses and consumer protection gaps.\nSuper Members Council chief executive Misha Schubert said stronger safeguards were urgently needed to restore confidence and reduce the risk of future failures.\n“Right now, safety gaps in some parts of the super system are being exploited, putting Australians at serious risk of losing the money they’ve worked hard their whole lives to save for retirement,” Schubert said.\n“We urgently need to level the playing field and lift protections and accountability in the parts of the system where they are weakest, bringing them up to the same high level as the strong safeguards that apply in mainstream super funds – so that every Australian can have confidence their super is safe, protected and working hard in their best interests.”\nThe industry body warned aggressive lead generation campaigns, conflicted remuneration arrangements and high-pressure sales tactics had enabled Australians to be funnelled out of regulated super products and into higher-risk investments.\nUnder its proposed reforms, the council called for stronger governance obligations on platforms, mandatory due diligence requirements, tighter controls on advice fee deductions and restrictions on conflicted payments tied to product access.\nIt also advocated for mandatory warnings and knowledge checks for SMSF trustees, alongside stronger regulatory visibility over switching activity and fund flows.\nThe submission also linked delays to the Delivering Better Financial Outcomes reforms with growing consumer vulnerability, arguing limited access to affordable advice was leaving Australians more exposed to predatory conduct.\nAccording to APRA data cited by the council, advice fee deductions from super rose from $1.464 billion in 2020 to $2.975 billion in 2025, with a sharp increase over the past two years concentrated in platform channels.\nThe submission also referenced ASIC Report 781, which warned of “inappropriate balance erosion” and identified weaknesses in trustee oversight processes tied to advice fee charging arrangements.\nSchubert said passing the DBFO reforms would help close the affordable advice gap and strengthen consumer protections.\n“Millions of low- and middle-income Australians also urgently need the promised DBFO reforms to become law to unlock access to safe, affordable guidance and advice from their own trusted super funds,” she said.\n“They are a key consumer protection measure in their own right that will help protect Australians from predatory social media ads and high-pressure sales.”",
  "summary": "",
  "publication": "Super Review",
  "author": "Adrian Suljanovic",
  "published_date": "2026-05-28T00:06:15+00:00",
  "word_count": "",
  "heading": "Superannuation and Investments",
  "newsletter": "Actuaries Institute Today",
  "factiva_url": "https://global.factiva.com/redir/default.aspx?EP=NL&AN=WCSPREW020260528em5s00001&CAT=W&napc=MC&f=nv&P=er&erc=LVfLdDTapCBrFH93tOPKccHd3xazgTKFnVNXLS29ADZY2C%2b%2fttJUlid%2b9IIvRWK0KjlYhDWeer5UCADTP3xoC4d3%2b7AN8ryemZLjvR9r3DyWz%2fAejrhTJexHaVQuG7bGa%2blsjoZO47iUv5iaNShDKx5w6vo0FFlHzoHknDNr675oJqDmi7JZ9S5APr%2fC%2bsCG0bAxyfU2bMq6IEvyAlmXX6MqLKuY87Vq%7c2&nldtl=DkzATV7FuEELjedX88l%2bbTt6lBYNjNrSx2D3jDckwHXkhG%2f6ivvzpde5Huy7QPKBW9ijHmQSMJ7k1UrVy0DIsjSoi1diK5RiEzc0DouQH7X2RtYkHOro6bp4FuWgYu%2fzG6WdEcPaiMpETz2uXQS3YQ%3d%3d%7c2&mod=MCT_email&page_driver=MCT_email",
  "final_url": "https://www.superreview.com.au/smc-demands-tougher-super-safeguards-following-billion-dollar-failures/",
  "redirected_to_source": true,
  "page_title": "SMC demands tougher super safeguards following billion-dollar failures - Super Review",
  "selector_used": "trafilatura"
}