{
  "id": "AUSTLN0020260504em5500013",
  "index": 9,
  "scraped_at": "2026-05-04T23:19:20Z",
  "title": "GPs want to monitor kids’ first five years",
  "full_text": "Other Editions 05 May 2026 TheNation GPs want to monitor kids’ first five years The Australian Robyn Riley 5 May 2026 566 words English AUSTLN 7 © News Pty Limited. No redistribution is permitted. Australia’s 50,000 general practitioners want every child to have a free annual health check until the age of five. The Royal Australian College of General Practitioners, the peak body for general practice, says the hour-long, Medicare-funded visit is critical to children’s long-term health and social outcomes. The RACGP wants an ­inclusive program of longer consults for every child for the first 2000 days of their life. If funded in next Tuesday’s federal budget, the initiative would be an Australian first. The RACGP says the comprehensive health assessments could help identify developmental concerns. They would also help GPs deliver Thriving Kids, a new national program to support children aged eight and under with developmental delay and autism outside the National Disability Insurance Scheme, but also be a general health check for every child. The call comes as experts warn the health of children is at a crossroads – the worst in a generation – but that early intervention can move the dial. On Monday, the Murdoch Children’s Research Institute revealed a bold four-point plan to reverse the trend. Experts say one in four Australian children are obese or overweight, they are sleeping one hour less a night, and they are not moving. MCRI director Kathryn North says for the first time in a generation children’s health is worse than that of their parents. She says MCRI wants to reverse that trend, “at scale, speed and low cost”. The RACGP said the cost of its proposal to extend the Medicare Benefits Schedule to support the annual checks for the first five years of a child’s life would be $160m over four years. RACGP president Michael Wright said children who receive support early are more likely to engage positively in school, reducing the need for more costly extra educational or healthcare interventions. “The first 2000 days of a child’s life shape their future,” Dr Wright said. “GPs are uniquely placed to identify developmental concerns early, support families and co-ordinate care, but they need the right tools and funding. This investment would ­ensure children get the support they need at the right time, rather than waiting until challenges become harder and more expensive to address.” Dr Tim Jones chairs the RACGP’s Specific Interest Child and Young Person’s Health group. The Tasmanian GP said early intervention was crucial and that all families should feel the health system understood the needs their children had at different ages and stages. “This proposal is for every child and for every parent in Australia, because during even the most typical of developmental journeys there will be stressed parents at some ­stages, and there doesn’t have to be a difference in development for families to feel like they’re entitled to get some extra care and support,” he said. Dr Jones said the proposal was for the first five years of a child’s life because this was when development was most dynamic. “Small changes make big impacts after five if you have found families early and given them timely support,” he said. “Change is still possible (after the age of five), but it’s a lot harder because kids’ patterns of learning, doing things and understanding the world have started to become more formed.” The Australian-20260505-Australian-7-000500670577 Nationwide News Pty Ltd. Document AUSTLN0020260504em5500013 Data Science and AI AFCA in no rush on AI tools InsuranceNEWS.com.au04 May 2026 04:18 GMT194 words The Australian Financial Complaints Authority is “taking a very slow approach” to using artificial intelligence to support handling life insurance disputes. General Insurance How consolidation is reshaping Australian insurance Insurance Business Online04 May 2026 05:00 GMT305 wordsMatthew Sellers and Daniel Wood For most of the past century, if you lived in Queensland and wanted home or motor insurance, you likely dealt with RACQ. If you were in South Australia, RAA Insurance was the natural first choice. If you were in Western Australia, RAC ... Cbus members to see 46% increase in insurance fees Financial Standard04 May 2026 04:38 GMT506 wordsELIZA BAVIN Cbus members will see an average 46% increase in death and TPD premiums from July 1. Default cover premiums will increase between $0.19 cents and $10.24 per week. NSW committee calls for reforms after CTP review InsuranceNEWS.com.au04 May 2026 04:36 GMT391 words The latest NSW compulsory third party scheme review has recommended trauma training for all claims managers and a requirement for insurers to make clear how people can participate in decision reviews. NIBA to present small business insurance proposals to committee Insurance Business Online03 May 2026 21:53 GMT317 wordsRoxanne Libatique The National Insurance Brokers Association of Australia (NIBA) will appear before a federal parliamentary inquiry to set out its proposals on how small businesses and not-for-profit organisations access and purchase insurance. NIBA ... Parametric is rewriting the cyclone claims clock Insurance Business Online04 May 2026 05:00 GMT221 wordsDaniel Wood When Severe Tropical Cyclone Narelle tore across Queensland, the Northern Territory and Western Australia in mid-March, traditional property insurers and their brokers were doing what they always do - waiting for the wind to drop, the roads... NSW and Victoria face ‘ominous conditions’ as storms persist Insurance Business Online03 May 2026 23:41 GMT548 wordsRoxanne Libatique Insurers are on standby as New South Wales and Victoria manage the impacts of storms, heavy rain, and falling temperatures that increased short‑term flood and wind risk across both states on Monday and may leave a legacy of claims into ... Health and Disability Insurance Seniors to cop a $1600 health cover hike Daily Telegraph05 May 2026279 wordsJulie Cross Older Australians are facing private health insurance price hikes of more than $1600 from April next year, under the Albanese government’s plan to scrap higher rebates for over-65s. GPs want to monitor kids’ first five years The Australian05 May 2026566 wordsRobyn Riley Australia’s 50,000 general practitioners want every child to have a free annual health check until the age of five. The Royal Australian College of General Practitioners, the peak body for general practice, says the hour-long, ... Superannuation and Investments Budget to tighten super tax breaks and housing incentives Super Review04 May 2026 01:29 GMT541 wordsAdrian Suljanovic As Australia approaches the 2026 Federal Budget, investors are preparing for a policy landscape shaped by fiscal repair, cost-of-living pressures and structural reform, with superannuation settings emerging as a key focus. Super funds score win on stamp duty disclosure Financial Standard04 May 2026 04:38 GMT357 wordsJAMIE WILLIAMSON The way in which super funds will have to disclose stamp duty as part of fees and costs to members is changing from July. From July 1, stamp duty paid in one year will be disclosed over the following seven years in fees and costs summaries ... Public trustee appointments proposed Financial Standard04 May 2026 06:10 GMT580 wordsJason Spits A proposed change to laws regarding who can be appointed as a trustee of an SMSF could allow individuals approved by a state or territory public trustee office to act in that capacity and claim remuneration for doing so, a specialist lawyer... AMP Bank rejigs LRBA product Financial Standard04 May 2026 06:06 GMT408 wordsJason Spits AMP has changed its SMSF limited recourse borrowing arrangement (LRBA) lending policies, reducing the minimum loan size and net asset thresholds that applied when it re-entered the residential LRBA lending space earlier this year. Regulation Judgment reserved in ASIC case against IAG InsuranceNEWS.com.au04 May 2026 05:25 GMT96 words Federal Court hearings have concluded in the Australian Securities and Investments Commission case against IAG over home insurance loyalty discounts. APRA data sheds light on dispute outcomes InsuranceNEWS.com.au04 May 2026 04:18 GMT202 words Life insurers resolved up to 95% of claims disputes, kept initial decisions in more than half of resolved accident cases and reversed outcomes in 4% of trauma complaint files last year, according to prudential data. Banking and Economy ‘Big trouble’: RBA poised to unleash rate rise blitz theaustralian.com.au04 May 2026 00:26 GMT642 wordsDuncan Evans The Reserve Bank of Australia could deliver multiple rate hikes to try and stop a “runaway train” of entrenched inflation, economists have warned ahead of tomorrow’s meeting. Budget to prioritise savings over spending The Age04 May 2026910 wordsShane Wright | Senior economics cor Billions in extra revenue generated by high-priced commodities such as oil and gas because of the war against Iran will be saved rather than spent as the Albanese government seeks to quell inflationary pressures that are poised to force ... Bourse falls again ahead of looming RBA rates call The Australian05 May 2026619 wordsIke Morris, Equities Fears of further interest rate pain and unfavourable company announcements continued the sell-off of the Australian sharemarket on Monday. The ASX 200 closed lower, dropping 32.7 points, or 0.38 per cent, to 8697.1, while the broader All ... Australia more favourable for private debt: Metrics The Australian04 May 2026499 wordsDavid Ross A leading figure in Australia’s private credit market has warned comparisons with US private lenders miss the point, and the domestic market is structurally more favourable to investors. ‘Can’t waste a crisis’: NAB’s reform call The Australian05 May 2026727 wordsDavid Ross National Australia Bank chief executive Andrew Irvine said his business customers should be free to raise their prices, because the alternative is even worse for the economy. If you have any questions regarding the Actuaries Institute news summary, or would like to unsubscribe, please contact comms@actuaries.asn.au . Any other unsubscribe links are currently non-functioning. © 2026 Factiva, Inc. All rights reserved. Terms of Use | Privacy Notice | Cookie Notice.",
  "summary": "The Royal Australian College of General Practitioners is advocating for annual free health checks for children up to five years old, funded by Medicare. This initiative aims to improve long-term health outcomes and identify developmental concerns early. The proposal, costing $160 million over four years, seeks to address alarming trends in children's health, including rising obesity rates and inadequate sleep.",
  "publication": "Seniors to cop a $1600 health cover hike\nDaily Telegraph05 May 2026279 wordsJulie Cross\n\nOlder Australians are facing private health insurance price hikes of more than $1600 from April next year, under the Albanese government’s plan to scrap higher rebates for over-65s.",
  "author": "",
  "published_date": "2026-05-05",
  "word_count": "566",
  "language": "English",
  "category": "News",
  "category_code": "A",
  "heading": "Health and Disability Insurance",
  "newsletter": "Actuaries Institute Today",
  "factiva_url": "https://global.factiva.com/redir/default.aspx?EP=NL&AN=AUSTLN0020260504em5500013&CAT=A&napc=MC&f=nv&P=er&erc=LVfLdDTapCBrFH93tOPKccHd3xazgTKFnVNXLS29ADZY2C%2b%2fttJUlgNslXJAbEzyy5sixj%2bpBzKoFa8xSrUs2jsSjj4K0Atod%2bpwJp1B24GVrKTWx6tRZbEaLffMTDtBeKhOEm5Vmo4QjSsa51uD62wjwKwGVsfO8tWZ3uq0cjUonWEQITtBMt%2f4HfjPIRmq7sfT%2fRyAZLGnEwpSt6%2bXLkn1Otz6MxvG%7c2&nldtl=DkzATV7FuEELjedX88l%2bbTt6lBYNjNrSx2D3jDckwHXkhG%2f6ivvzpde5Huy7QPKBoVBkcnhBHRHmHfRe%2bwRIKc0rfSP4eVA%2bMUAkkwyQl0yqYeQm7qJL2CSROEYZCJt4Vjcaj%2bBLg%2fAKUS0lfyqGyg%3d%3d%7c2&mod=MCT_email&page_driver=MCT_email",
  "final_url": "https://viewer.factiva.com/Edition?an=AUSTLN0020260504em5500013&mod=MCT_email&page_driver=MCT_email&CAT=A&napc=MC&erc=LVfLdDTapCBrFH93tOPKccHd3xazgTKFnVNXLS29ADZY2C%2B%2FttJUlgNslXJAbEzyy5sixj%2BpBzKoFa8xSrUs2jsSjj4K0Atod%2BpwJp1B24GVrKTWx6tRZbEaLffMTDtBeKhOEm5Vmo4QjSsa51uD62wjwKwGVsfO8tWZ3uq0cjUonWEQITtBMt%2F4HfjPIRmq7sfT%2FRyAZLGnEwpSt6%2BXLkn1Otz6MxvG%7C2&editionId=13581161&templateId=34197&trackProfileName=Actuaries%20Institute&eid4=dli4bWDCZhDfmWc_2B9tjsISl5WHoXTpFWNrH597v4uy6J84BDHeLvZdMrLhtPukx2AI3gexMYJcdhgMpEGjZUTOQSo1aW7wUwtlKnjKqJS3VOUkNf5h0wHkspXwgTzdu1gX_2FpmVzJZobQx11Hp4LH3rSWXyg4eSNauIuDkI_2BN8bbYOELSRACJ2w_3D_3D%7C2&nldtl=DkzATV7FuEELjedX88l%20bTt6lBYNjNrSx2D3jDckwHXkhG%2F6ivvzpde5Huy7QPKBoVBkcnhBHRHmHfRe%20wRIKc0rfSP4eVA%20MUAkkwyQl0yqYeQm7qJL2CSROEYZCJt4Vjcaj%20BLg%2FAKUS0lfyqGyg%3D%3D%7C2",
  "redirected_to_source": false,
  "page_title": "Dow Jones Newsletter",
  "selector_used": "body",
  "key_points": [
    "RACGP calls for annual Medicare-funded health checks for children until age five.",
    "Proposal aims to identify developmental issues early and support overall child health.",
    "Cost of the initiative is estimated at $160 million over four years."
  ],
  "tags": [
    "child health",
    "medicare",
    "health policy",
    "developmental support"
  ],
  "relevance": "This initiative highlights the financial implications of health policies that may affect future healthcare costs and insurance models in Australia.",
  "summarised": true
}